devsecops/__about__.py
devsecops/__init__.py
devsecops/base/__init__.py
devsecops/base/base_handler.py
devsecops/cli/__init__.py
devsecops/cli/opts.py
devsecops/cli/services/__init__.py
devsecops/cli/services/nexus.py
devsecops/cli/services/quay.py
devsecops/cli/services/sonarqube.py
devsecops/nexus/__init__.py
devsecops/nexus/nexus.py
devsecops/quay/__init__.py
devsecops/quay/quay.py
devsecops/sonarqube/__init__.py
devsecops/sonarqube/sonarqube.py
devsecops_api-0.2.0.dist-info/LICENSE
devsecops_api-0.2.0.dist-info/METADATA
devsecops_api-0.2.0.dist-info/WHEEL
devsecops_api-0.2.0.dist-info/entry_points.txt
devsecops_api-0.2.0.dist-info/top_level.txt
devsecops_api-0.2.0.dist-info/RECORD
