Metadata-Version: 2.1
Name: devsecops-api
Version: 0.2.0
Summary: DevSecOps Workshop API Collection
Home-page: https://github.com/RedHatGov/devsecops-api-collection
Author: James Harmison
Author-email: jharmison@redhat.com
License: BSD-2-Clause
Keywords: devsecops redhat openshift
Platform: UNKNOWN
Classifier: Development Status :: 2 - Pre-Alpha
Classifier: Intended Audience :: Information Technology
Classifier: Intended Audience :: Developers
Classifier: License :: OSI Approved :: BSD License
Classifier: Programming Language :: Python :: 3
Classifier: Programming Language :: Python :: 3.6
Classifier: Programming Language :: Python :: 3.7
Requires-Python: >=3.6
Requires-Dist: click
Requires-Dist: requests
